lzy/__init__.py
lzy/lzy-servant.jar
lzy/startup.py
lzy/api/__init__.py
lzy/api/buses.py
lzy/api/env.py
lzy/api/lazy_op.py
lzy/api/server.py
lzy/api/utils.py
lzy/api/_proxy/__init__.py
lzy/api/_proxy/automagic.py
lzy/api/pkg_info/__init__.py
lzy/api/whiteboard/__init__.py
lzy/api/whiteboard/controller.py
lzy/api/whiteboard/field.py
lzy/api/whiteboard/repo.py
lzy/api/whiteboard/wb.py
lzy/model/channel.py
lzy/model/env.py
lzy/model/file_slots.py
lzy/model/slot.py
lzy/model/zygote.py
lzy/model/zygote_python_func.py
lzy/servant/bash_servant.py
lzy/servant/servant.py
lizy-0.0.1.dist-info/METADATA
lizy-0.0.1.dist-info/WHEEL
lizy-0.0.1.dist-info/top_level.txt
lizy-0.0.1.dist-info/RECORD
