Metadata-Version: 2.1
Name: lizy
Version: 0.0.1
Summary: UNKNOWN
Home-page: UNKNOWN
Author: lzy developers
License: UNKNOWN
Platform: UNKNOWN
Requires-Python: >=3.7
Requires-Dist: cloudpickle (==2.0.0)
Requires-Dist: pyyaml
